proxypypi
