Metadata-Version: 1.0
Name: proxypypi
Version: 1.2.2
Summary: A PyPI caching proxy
Home-page: https://bitbucket.org/r1chardj0n3s/proxypypi
Author: Richard Jones
Author-email: rjones@ekit-inc.com
License: BSD
Platform: UNKNOWN
